LICENSE
MANIFEST.in
README.md
requirements.txt
setup.py
CoinPaca_lib.egg-info/PKG-INFO
CoinPaca_lib.egg-info/SOURCES.txt
CoinPaca_lib.egg-info/dependency_links.txt
CoinPaca_lib.egg-info/top_level.txt
src/__init__.py
src/validators.py