Metadata-Version: 2.1
Name: CoinPaca-lib
Version: 1.0.0
Summary: Common library for the CoinPaca project
Home-page: https://gitlab.com/CoinPaca/core/lib
Author: Patrik Katrenak
Author-email: patrik@katryapps.com
Platform: any
Classifier: Programming Language :: Python :: 3
Classifier: Operating System :: OS Independent
Classifier: Natural Language :: English
Requires-Python: >=3.10
License-File: LICENSE
